emus_web/__init__.py
emus_web/apps/activitypub/__init__.py
emus_web/apps/activitypub/exceptions.py
emus_web/apps/activitypub/models.py
emus_web/apps/activitypub/signatures.py
emus_web/apps/activitypub/utils.py
emus_web/apps/activitypub/views.py
emus_web/apps/games/__init__.py
emus_web/apps/games/admin.py
emus_web/apps/games/api/__init__.py
emus_web/apps/games/api/serializers.py
emus_web/apps/games/api/views.py
emus_web/apps/games/apps.py
emus_web/apps/games/constants.py
emus_web/apps/games/context_processors.py
emus_web/apps/games/management/__init__.py
emus_web/apps/games/management/commands/__init__.py
emus_web/apps/games/management/commands/export_collections.py
emus_web/apps/games/management/commands/export_gamelist_xml_file.py
emus_web/apps/games/management/commands/import_gamelist_xml_file.py
emus_web/apps/games/management/commands/scrape_roms.py
emus_web/apps/games/management/commands/update_roms.py
emus_web/apps/games/migrations/0001_initial.py
emus_web/apps/games/migrations/0002_alter_game_players.py
emus_web/apps/games/migrations/0003_alter_game_developer_alter_game_publisher.py
emus_web/apps/games/migrations/0004_game_english_patched_game_english_patched_version_and_more.py
emus_web/apps/games/migrations/0005_game_region_game_undub.py
emus_web/apps/games/migrations/0006_alter_game_region.py
emus_web/apps/games/migrations/0007_alter_game_marquee_alter_game_region_and_more.py
emus_web/apps/games/migrations/0008_game_featured.py
emus_web/apps/games/migrations/0009_developer_created_developer_modified_game_created_and_more.py
emus_web/apps/games/migrations/0010_alter_game_release_date.py
emus_web/apps/games/migrations/0011_alter_game_region.py
emus_web/apps/games/migrations/0012_alter_game_marquee_alter_game_rom_file_and_more.py
emus_web/apps/games/migrations/0013_alter_game_screenshot.py
emus_web/apps/games/migrations/0014_alter_developer_options_alter_game_options_and_more.py
emus_web/apps/games/migrations/0015_gamecollection.py
emus_web-0.1.0.dist-info/entry_points.txt
emus_web-0.1.0.dist-info/WHEEL
emus_web-0.1.0.dist-info/METADATA
emus_web-0.1.0.dist-info/RECORD
