Metadata-Version: 2.1
Name: emus-web
Version: 0.1.0
Summary: A hacky web frontend for Emulation Station rom collections
Author: Colin Powell
Author-email: colin@unbl.ink
Requires-Python: >=3.8,<4.0
Classifier: Programming Language :: Python :: 3
Classifier: Programming Language :: Python :: 3.8
Classifier: Programming Language :: Python :: 3.9
Classifier: Programming Language :: Python :: 3.10
Classifier: Programming Language :: Python :: 3.11
Requires-Dist: Django (>=4.0.3,<5.0.0)
Requires-Dist: Markdown (>=3.3.6,<4.0.0)
Requires-Dist: Pillow (>=9.0.1,<10.0.0)
Requires-Dist: colorlog (>=6.6.0,<7.0.0)
Requires-Dist: dj-database-url (>=0.5.0,<0.6.0)
Requires-Dist: django-allauth (>=0.50.0,<0.51.0)
Requires-Dist: django-celery-results (>=2.3.0,<3.0.0)
Requires-Dist: django-extensions (>=3.1.5,<4.0.0)
Requires-Dist: django-filter (>=21.1,<22.0)
Requires-Dist: django-markdownify (>=0.9.1,<0.10.0)
Requires-Dist: django-mathfilters (>=1.0.0,<2.0.0)
Requires-Dist: django-simple-history (>=3.1.1,<4.0.0)
Requires-Dist: django-taggit (>=2.1.0,<3.0.0)
Requires-Dist: djangorestframework (>=3.13.1,<4.0.0)
Requires-Dist: gunicorn (>=20.1.0,<21.0.0)
Requires-Dist: psycopg2[production] (>=2.9.3,<3.0.0)
Requires-Dist: python-dateutil (>=2.8.2,<3.0.0)
Requires-Dist: python-dotenv (>=0.20.0,<0.21.0)
Requires-Dist: python-json-logger (>=2.0.2,<3.0.0)
Requires-Dist: redis (>=4.2.2,<5.0.0)
Requires-Dist: whitenoise (>=6.3.0,<7.0.0)
